gridfinder-3.1.2.dist-info/METADATA
gridfinder-3.1.2.dist-info/WHEEL
gridfinder-3.1.2.dist-info/licenses/LICENSE
gridfinder/__init__.py
gridfinder/gridfinder.py
gridfinder/post.py
gridfinder/prepare.py
gridfinder/py.typed
gridfinder/util.py
gridfinder-3.1.2.dist-info/RECORD
