Metadata-Version: 2.1
Name: gridfinder
Version: 3.1.2
Summary: Algorithm for guessing MV grid network based on night time lights
Keywords: ntl,electricity,grid
Home-page: https://gridfinder.rdrn.me
Author-Email: Chris Arderne <chris@rdrn.me>
License: MIT License
Classifier: Environment :: Console
Classifier: License :: OSI Approved :: MIT License
Classifier: Operating System :: OS Independent
Classifier: Programming Language :: Python :: 3
Classifier: Programming Language :: Python :: 3.9
Classifier: Programming Language :: Python :: 3.10
Classifier: Programming Language :: Python :: 3.11
Classifier: Programming Language :: Python :: 3.12
Project-URL: Homepage, https://gridfinder.rdrn.me
Project-URL: Repository, https://github.com/carderne/gridfinder
Requires-Python: >=3.9
Requires-Dist: affine~=2.4
Requires-Dist: click~=8.0
Requires-Dist: fiona~=1.9
Requires-Dist: geopandas~=0.14
Requires-Dist: numba~=0.58
Requires-Dist: numpy~=1.26
Requires-Dist: pandas~=2.2
Requires-Dist: pillow~=10.2
Requires-Dist: pyarrow~=15.0
Requires-Dist: pyproj~=3.6
Requires-Dist: rasterio~=1.3
Requires-Dist: Rtree~=1.2
Requires-Dist: scikit-image~=0.22
Requires-Dist: scipy~=1.12
Requires-Dist: Shapely~=2.0
